[
  {
    "brand": "Warcolours",
    "brandData": {},
    "category": "",
    "discontinued": false,
    "hex": "#70C8F0",
    "id": "warcolours-opaque-baby-blue",
    "impcat": {},
    "name": "Baby Blue",
    "range": "One Coat",
    "sku": "WC-ONE-BABYBLUE",
    "type": "opaque",
    "url": "https://www.warcolours.com/"
  },
  {
    "brand": "Warcolours",
    "brandData": {},
    "category": "",
    "discontinued": false,
    "hex": "#E8D098",
    "id": "warcolours-opaque-beige",
    "impcat": {},
    "name": "Beige",
    "range": "One Coat",
    "sku": "WC-ONE-BEIGE",
    "type": "opaque",
    "url": "https://www.warcolours.com/"
  },
  {
    "brand": "Warcolours",
    "brandData": {},
    "category": "",
    "discontinued": false,
    "hex": "#000000",
    "id": "warcolours-opaque-black",
    "impcat": {},
    "name": "Black",
    "range": "One Coat",
    "sku": "WC-ONE-BLACK",
    "type": "opaque",
    "url": "https://www.warcolours.com/"
  },
  {
    "brand": "Warcolours",
    "brandData": {},
    "category": "",
    "discontinued": false,
    "hex": "#2040E0",
    "id": "warcolours-opaque-blue",
    "impcat": {},
    "name": "Blue",
    "range": "One Coat",
    "sku": "WC-ONE-BLUE",
    "type": "opaque",
    "url": "https://www.warcolours.com/"
  },
  {
    "brand": "Warcolours",
    "brandData": {},
    "category": "",
    "discontinued": false,
    "hex": "#D8B030",
    "id": "warcolours-opaque-gold",
    "impcat": {},
    "name": "Gold",
    "range": "One Coat",
    "sku": "WC-ONE-GOLD",
    "type": "opaque",
    "url": "https://www.warcolours.com/"
  },
  {
    "brand": "Warcolours",
    "brandData": {},
    "category": "",
    "discontinued": false,
    "hex": "#20E020",
    "id": "warcolours-opaque-green",
    "impcat": {},
    "name": "Green",
    "range": "One Coat",
    "sku": "WC-ONE-GREEN",
    "type": "opaque",
    "url": "https://www.warcolours.com/"
  },
  {
    "brand": "Warcolours",
    "brandData": {},
    "category": "",
    "discontinued": false,
    "hex": "#888888",
    "id": "warcolours-opaque-grey",
    "impcat": {},
    "name": "Grey",
    "range": "One Coat",
    "sku": "WC-ONE-GREY",
    "type": "opaque",
    "url": "https://www.warcolours.com/"
  },
  {
    "brand": "Warcolours",
    "brandData": {},
    "category": "",
    "discontinued": false,
    "hex": "#E818A0",
    "id": "warcolours-opaque-magenta",
    "impcat": {},
    "name": "Magenta",
    "range": "One Coat",
    "sku": "WC-ONE-MAGENTA",
    "type": "opaque",
    "url": "https://www.warcolours.com/"
  },
  {
    "brand": "Warcolours",
    "brandData": {},
    "category": "",
    "discontinued": false,
    "hex": "#C89028",
    "id": "warcolours-opaque-ochre",
    "impcat": {},
    "name": "Ochre",
    "range": "One Coat",
    "sku": "WC-ONE-OCHRE",
    "type": "opaque",
    "url": "https://www.warcolours.com/"
  },
  {
    "brand": "Warcolours",
    "brandData": {},
    "category": "",
    "discontinued": false,
    "hex": "#F08010",
    "id": "warcolours-opaque-orange",
    "impcat": {},
    "name": "Orange",
    "range": "One Coat",
    "sku": "WC-ONE-ORANGE",
    "type": "opaque",
    "url": "https://www.warcolours.com/"
  },
  {
    "brand": "Warcolours",
    "brandData": {},
    "category": "",
    "discontinued": false,
    "hex": "#F868B0",
    "id": "warcolours-opaque-pink",
    "impcat": {},
    "name": "Pink",
    "range": "One Coat",
    "sku": "WC-ONE-PINK",
    "type": "opaque",
    "url": "https://www.warcolours.com/"
  },
  {
    "brand": "Warcolours",
    "brandData": {},
    "category": "",
    "discontinued": false,
    "hex": "#A020A0",
    "id": "warcolours-opaque-purple",
    "impcat": {},
    "name": "Purple",
    "range": "One Coat",
    "sku": "WC-ONE-PURPLE",
    "type": "opaque",
    "url": "https://www.warcolours.com/"
  },
  {
    "brand": "Warcolours",
    "brandData": {},
    "category": "",
    "discontinued": false,
    "hex": "#E01818",
    "id": "warcolours-opaque-red",
    "impcat": {},
    "name": "Red",
    "range": "One Coat",
    "sku": "WC-ONE-RED",
    "type": "opaque",
    "url": "https://www.warcolours.com/"
  },
  {
    "brand": "Warcolours",
    "brandData": {},
    "category": "",
    "discontinued": false,
    "hex": "#F04010",
    "id": "warcolours-opaque-red-orange",
    "impcat": {},
    "name": "Red Orange",
    "range": "One Coat",
    "sku": "WC-ONE-REDORANGE",
    "type": "opaque",
    "url": "https://www.warcolours.com/"
  },
  {
    "brand": "Warcolours",
    "brandData": {},
    "category": "",
    "discontinued": false,
    "hex": "#B0B0B0",
    "id": "warcolours-opaque-silver",
    "impcat": {},
    "name": "Silver",
    "range": "One Coat",
    "sku": "WC-ONE-SILVER",
    "type": "opaque",
    "url": "https://www.warcolours.com/"
  },
  {
    "brand": "Warcolours",
    "brandData": {},
    "category": "",
    "discontinued": false,
    "hex": "#20D8C0",
    "id": "warcolours-opaque-turquoise",
    "impcat": {},
    "name": "Turquoise",
    "range": "One Coat",
    "sku": "WC-ONE-TURQUOISE",
    "type": "opaque",
    "url": "https://www.warcolours.com/"
  },
  {
    "brand": "Warcolours",
    "brandData": {},
    "category": "",
    "discontinued": false,
    "hex": "#7020D0",
    "id": "warcolours-opaque-violet",
    "impcat": {},
    "name": "Violet",
    "range": "One Coat",
    "sku": "WC-ONE-VIOLET",
    "type": "opaque",
    "url": "https://www.warcolours.com/"
  },
  {
    "brand": "Warcolours",
    "brandData": {},
    "category": "",
    "discontinued": false,
    "hex": "#FFFFFF",
    "id": "warcolours-opaque-white",
    "impcat": {},
    "name": "White",
    "range": "One Coat",
    "sku": "WC-ONE-WHITE",
    "type": "opaque",
    "url": "https://www.warcolours.com/"
  },
  {
    "brand": "Warcolours",
    "brandData": {},
    "category": "",
    "discontinued": false,
    "hex": "#F8F010",
    "id": "warcolours-opaque-yellow",
    "impcat": {},
    "name": "Yellow",
    "range": "One Coat",
    "sku": "WC-ONE-YELLOW",
    "type": "opaque",
    "url": "https://www.warcolours.com/"
  },
  {
    "brand": "Warcolours",
    "brandData": {},
    "category": "",
    "discontinued": false,
    "hex": "#98E020",
    "id": "warcolours-opaque-yellow-green",
    "impcat": {},
    "name": "Yellow Green",
    "range": "One Coat",
    "sku": "WC-ONE-YELLOWGREEN",
    "type": "opaque",
    "url": "https://www.warcolours.com/"
  }
]